__init__.py
app.py
models.py
setup.py
test.py
update_version.py
tiddly.egg-info/PKG-INFO
tiddly.egg-info/SOURCES.txt
tiddly.egg-info/dependency_links.txt
tiddly.egg-info/requires.txt
tiddly.egg-info/top_level.txt